[{"start":"2018-06-29T17:00:00.000Z","team1":"Team Not Found.","team1_points":0,"team2":"KillaBeez","team2_points":2,"winner":false},{"start":"2018-06-29T16:00:00.000Z","team1":"RedLynX","team1_points":1,"team2":"Team Not Found.","team2_points":0,"winner":true},{"start":"2018-06-29T17:00:00.000Z","team1":"Team Not Found.","team1_points":1,"team2":"KillaBeez","team2_points":2,"winner":false},{"start":"2018-06-29T16:00:00.000Z","team1":"RedLynX","team1_points":5,"team2":"Team Not Found.","team2_points":2,"winner":true}]